statsbombpy/__init__.py
statsbombpy/api_client.py
statsbombpy/config.py
statsbombpy/entities.py
statsbombpy/helpers.py
statsbombpy/public.py
statsbombpy/sb.py
statsbombpy-1.15.0.dist-info/METADATA
statsbombpy-1.15.0.dist-info/WHEEL
statsbombpy-1.15.0.dist-info/top_level.txt
statsbombpy-1.15.0.dist-info/RECORD
