Metadata-Version: 2.1
Name: statsbombpy
Version: 1.15.0
Summary: easily stream StatsBomb data into Python
Home-page: https://github.com/statsbomb/statsbombpy
Author: StatsBomb
Author-email: support@statsbombservices.com
Requires-Dist: pandas
Requires-Dist: requests
Requires-Dist: requests-cache
Requires-Dist: inflect
Requires-Dist: joblib
Provides-Extra: dev
Requires-Dist: nose2; extra == "dev"
